cracks/__init__.py
cracks/cracks.py
social_brute_force-0.0.1.dist-info/METADATA
social_brute_force-0.0.1.dist-info/WHEEL
social_brute_force-0.0.1.dist-info/top_level.txt
social_brute_force-0.0.1.dist-info/RECORD
