Metadata-Version: 2.1
Name: social-brute-force
Version: 0.0.1
Summary: social brute force.
Home-page: UNKNOWN
Author: Exso Kamabay
Author-email: lexyong66@gmail.com
License: UNKNOWN
Keywords: brute force,social
Platform: windows
Platform: linux
Platform: macos
Requires-Dist: kmy-beautify (==0.6.0)
Requires-Dist: post-data (==4.0)
